{
  "asn": 215304,
  "handle": "YUWAN",
  "description": "YUWAN NETWORKS LIMITED",
  "subnets": {
    "ipv4": [
      "31.56.84.0/24",
      "31.57.104.0/24",
      "82.152.142.0/24",
      "202.155.123.0/24",
      "202.155.152.0/24",
      "202.155.155.0/24",
      "212.100.174.0/24"
    ],
    "ipv6": [
      "2602:f921:f02::/47",
      "2602:f921:f04::/46",
      "2602:f921:f0b::/48",
      "2a0f:7802:e207::/48",
      "2a0f:7802:e208::/47",
      "2a0f:7802:e2a0::/47",
      "2a0f:7802:e2b0::/48",
      "2a0f:7802:e2b2::/47",
      "2a0f:7802:e2bf::/48",
      "2a0f:7802:e2c0::/47",
      "2a0f:7802:e2d2::/47",
      "2a0f:7802:e2e5::/48",
      "2a0f:7802:e2f0::/48",
      "2a0f:7802:e2f2::/48",
      "2a0f:7802:e2f4::/47",
      "2a0f:7802:e2fc::/47",
      "2a0f:7802:e2fe::/48",
      "2a0f:7803:fb40::/48",
      "2a0f:7803:fb48::/47",
      "2a0f:7803:fb4f::/48"
    ]
  }
}