{
  "asn": 202256,
  "handle": "LAWLIETNET",
  "description": "Dongyu Zhang",
  "subnets": {
    "ipv4": [],
    "ipv6": [
      "2a12:dd47:6029::/48",
      "2a12:dd47:603d::/48",
      "2a12:dd47:6050::/48",
      "2a12:dd47:60e8::/48",
      "2a12:dd47:60f0::/48",
      "2a12:dd47:6b1c::/48",
      "2a12:dd47:6b93::/48",
      "2a12:dd47:6bbd::/48",
      "2a12:dd47:6be8::/48",
      "2a12:dd47:6bf0::/48",
      "2a12:dd47:6e4a::/48",
      "2a12:dd47:6e7a::/48",
      "2a12:dd47:6e8e::/48",
      "2a12:dd47:6eba::/48",
      "2a12:dd47:6edb::/48",
      "2a12:dd47:c429::/48",
      "2a12:dd47:c447::/48",
      "2a12:dd47:c483::/48",
      "2a12:dd47:c4d2::/48",
      "2a12:dd47:c4e6::/48",
      "2a12:dd47:e04c::/48",
      "2a12:dd47:e061::/48",
      "2a12:dd47:e083::/48",
      "2a12:dd47:e096::/48",
      "2a12:dd47:e09d::/48"
    ]
  }
}