{
  "asn": 202256,
  "handle": "LAWLIETNET",
  "description": "Dongyu Zhang",
  "subnets": {
    "ipv4": [],
    "ipv6": [
      "2a12:dd47:6019::/48",
      "2a12:dd47:6080::/48",
      "2a12:dd47:60c5::/48",
      "2a12:dd47:60c6::/48",
      "2a12:dd47:60d6::/48",
      "2a12:dd47:6b1a::/48",
      "2a12:dd47:6b50::/48",
      "2a12:dd47:6b81::/48",
      "2a12:dd47:6b94::/48",
      "2a12:dd47:6bcf::/48",
      "2a12:dd47:c415::/48",
      "2a12:dd47:c428::/48",
      "2a12:dd47:c42c::/48",
      "2a12:dd47:c43c::/48",
      "2a12:dd47:c4cc::/48",
      "2a12:dd47:e01a::/48",
      "2a12:dd47:e01d::/48",
      "2a12:dd47:e028::/48",
      "2a12:dd47:e0a0::/48",
      "2a12:dd47:e0bf::/48",
      "2a12:dd47:e809::/48",
      "2a12:dd47:e80c::/48",
      "2a12:dd47:e828::/47",
      "2a12:dd47:e84b::/48"
    ]
  }
}