{
  "asn": 917,
  "handle": "MISAKA",
  "description": "Misaka Network Inc",
  "subnets": {
    "ipv4": [
      "38.175.96.0/21",
      "38.175.104.0/22",
      "38.175.108.0/23",
      "64.234.232.0/23",
      "64.234.234.0/24",
      "170.39.224.0/22",
      "199.119.65.0/24",
      "209.209.56.0/22"
    ],
    "ipv6": [
      "2a0b:4341:a0e::/48",
      "2a0b:4342:1a31::/48",
      "2a0b:4342:1a33::/48",
      "2a0b:4342:1a90::/48",
      "2a0b:4342:3000::/36",
      "2a0e:6901:100::/40",
      "2a0e:6901:200::/40",
      "2a0e:6901:400::/40",
      "2a0e:6901:504::/48",
      "2a0e:6902:2000::/36",
      "2a0e:6902:4000::/40",
      "2a0e:6902:5000::/36"
    ]
  }
}