{
  "asn": 134146,
  "handle": "SAMONLINE-AS-AP",
  "description": "SAM ONLINE",
  "subnets": {
    "ipv4": [
      "36.50.19.0/24",
      "103.55.144.0/22",
      "103.73.224.0/22",
      "103.206.231.0/24",
      "202.83.124.0/24",
      "202.83.126.0/24"
    ],
    "ipv6": [
      "2400:4fc0:3::/48",
      "2400:4fc0:4::/46",
      "2400:4fc0:8::/47",
      "2400:4fc0:b::/48",
      "2400:4fc0:d::/48",
      "2400:4fc0:e::/47",
      "2400:4fc0:10::/44",
      "2400:4fc0:20::/44",
      "2400:4fc0:30::/46",
      "2400:4fc0:34::/47",
      "2400:4fc0:37::/48",
      "2400:4fc0:39::/48",
      "2400:4fc0:3a::/48"
    ]
  }
}