{
  "asn": 54201,
  "handle": "WEWORK-MANAGEMENT-LLC",
  "description": "We Link Networks LLC",
  "subnets": {
    "ipv4": [
      "103.139.86.0/24",
      "199.47.72.0/22",
      "199.47.76.0/24",
      "199.47.79.0/24"
    ],
    "ipv6": [
      "2404:e4c0:8::/48",
      "2404:e4c0:1008::/48",
      "2404:e4c0:5105::/48",
      "2605:bc0::/47",
      "2605:bc0:800::/47",
      "2605:bc0:1005::/48",
      "2605:bc0:1014::/48",
      "2605:bc0:2002::/48",
      "2605:bc0:2008::/48",
      "2605:bc0:2134::/47",
      "2a0e:1b80:3::/48",
      "2a0e:1b80:1003::/48"
    ]
  }
}