{
  "asn": 42375,
  "handle": "NETEX",
  "description": "Netex Limited",
  "subnets": {
    "ipv4": [
      "91.191.191.0/24",
      "185.147.124.0/23"
    ],
    "ipv6": [
      "2001:67c:8c::/48",
      "2a04:fa00::/29",
      "2a06:7840::/29",
      "2a07:d940::/29",
      "2a09:2980::/29",
      "2a09:9300::/29",
      "2a09:ba40::/29",
      "2a0b:2a80::/29",
      "2a0c:1240::/29",
      "2a0d:4440::/29",
      "2a0d:48c0::/29",
      "2a0d:95c0::/29",
      "2a0d:9940::/29",
      "2a0e:4580::/29",
      "2a0f:f00::/32",
      "2a0f:f02::/31",
      "2a0f:f04::/30",
      "2a0f:4bc0::/29",
      "2a0f:5080::/29",
      "2a0f:59c0::/29",
      "2a0f:a380::/29",
      "2a0f:bf40::/29",
      "2a0f:e100::/29",
      "2a11:f40::/29",
      "2a11:1380::/29",
      "2a11:1480::/29",
      "2a11:1540::/29",
      "2a11:1580::/29",
      "2a11:15c0::/29",
      "2a11:1780::/29",
      "2a11:1a80::/29",
      "2a11:1f00::/29",
      "2a11:1fc0::/29",
      "2a11:2140::/29",
      "2a11:2540::/29",
      "2a11:3440::/29",
      "2a11:34c0::/29",
      "2a11:3640::/29",
      "2a11:3840::/29",
      "2a11:3e40::/29",
      "2a11:3fc0::/29",
      "2a11:4100::/29",
      "2a11:45c0::/29",
      "2a11:4a80::/29",
      "2a11:52c0::/29",
      "2a11:5480::/29",
      "2a11:6300::/29",
      "2a11:6640::/29",
      "2a11:7780::/29",
      "2a11:78c0::/29",
      "2a11:8940::/29",
      "2a11:8d80::/29",
      "2a11:8ec0::/29",
      "2a11:9380::/29",
      "2a11:c540::/29",
      "2a11:c700::/29",
      "2a11:fe00::/29",
      "2a12:15c0::/29",
      "2a12:19c0::/29",
      "2a12:1c40::/29",
      "2a12:24c0::/29",
      "2a12:25c0::/29",
      "2a12:2740::/29",
      "2a12:2bc0::/29",
      "2a12:2ec0::/29",
      "2a12:3400::/29",
      "2a12:34c0::/29",
      "2a12:35c0::/29",
      "2a12:3740::/29",
      "2a12:3940::/29",
      "2a12:3a40::/29",
      "2a12:3d40::/29",
      "2a12:3dc0::/29",
      "2a12:4140::/29",
      "2a12:41c0::/29",
      "2a12:4240::/29",
      "2a12:4500::/29",
      "2a12:46c0::/29",
      "2a12:5580::/29",
      "2a12:6600::/29",
      "2a12:8800::/29"
    ]
  }
}