{
  "asn": 24406,
  "handle": "CNNIC-CRITICAL-AP",
  "description": "China Internet Network Infomation Center",
  "subnets": {
    "ipv4": [
      "42.83.130.0/24",
      "42.83.132.0/23",
      "125.208.32.0/23",
      "125.208.34.0/24",
      "125.208.42.0/23",
      "125.208.44.0/24",
      "125.208.49.0/24",
      "203.119.26.0/23",
      "203.119.30.0/24"
    ],
    "ipv6": [
      "2001:dc7::/46",
      "2001:dc7:1000::/48",
      "2001:dc7:2dff::/48",
      "2001:dc7:feff::/48",
      "2001:dc7:ffc1::/48",
      "2001:dc7:ffc2::/47",
      "2001:dc7:ffd1::/48",
      "2001:dc7:ffd2::/47",
      "2001:dc7:fffb::/48",
      "2001:dc7:fffc::/46"
    ]
  }
}