{
  "asn": 45326,
  "handle": "BBTS-AS-AP",
  "description": "Broad Band Telecom Services Ltd",
  "subnets": {
    "ipv4": [
      "103.30.28.0/22",
      "119.18.144.0/21",
      "202.5.32.0/21",
      "202.5.40.0/22",
      "202.5.45.0/24",
      "202.5.46.0/23",
      "202.5.48.0/20"
    ],
    "ipv6": [
      "2401:8a40:1::/48",
      "2401:8a40:2::/47",
      "2401:8a40:5::/48",
      "2401:8a40:6::/48",
      "2401:8a40:14::/46",
      "2401:8a40:18::/45",
      "2401:8a40:20::/45",
      "2401:8a40:28::/46",
      "2401:8a40:38::/45",
      "2401:8a40:40::/43"
    ]
  }
}