{
  "asn": 204860,
  "handle": "NETX",
  "description": "NetX Networks a.s.",
  "subnets": {
    "ipv4": [
      "45.137.128.0/22",
      "45.147.164.0/22",
      "185.217.234.0/23",
      "192.144.44.0/22",
      "193.39.188.0/22",
      "194.180.110.0/24",
      "194.180.115.0/24",
      "194.180.150.0/24"
    ],
    "ipv6": [
      "2a07:6881::/32",
      "2a07:6886::/32",
      "2a07:ef40::/29",
      "2a09:380::/29",
      "2a0a:f0c0::/29",
      "2a0c:1580::/29",
      "2a0e:bc40::/29",
      "2a0f:2a80::/29",
      "2a0f:5880::/29"
    ]
  }
}