{
  "asn": 57433,
  "handle": "INTERCOLO",
  "description": "intercolo GmbH",
  "subnets": {
    "ipv4": [
      "37.114.33.0/24",
      "37.114.38.0/23",
      "37.114.44.0/24",
      "94.154.48.0/21",
      "176.100.39.0/24"
    ],
    "ipv6": [
      "2a00:ccc0::/32",
      "2a00:ccc1::/48",
      "2a00:ccc1:4::/48",
      "2a00:ccc1:2000::/45",
      "2a00:ccc1:2008::/47",
      "2a00:ccc1:2010::/45",
      "2a00:ccc1:2018::/47",
      "2a00:ccc1:2020::/45",
      "2a00:ccc1:2028::/47",
      "2a00:ccc1:2030::/45",
      "2a00:ccc1:2038::/47",
      "2a00:ccc1:2040::/45",
      "2a00:ccc1:2048::/47"
    ]
  }
}